hdob/__init__.py
hdob/hdob.py
hdob-1.0.5.dist-info/METADATA
hdob-1.0.5.dist-info/WHEEL
hdob-1.0.5.dist-info/entry_points.txt
hdob-1.0.5.dist-info/top_level.txt
hdob-1.0.5.dist-info/RECORD
